AUTHORS
LICENSE
MANIFEST.in
README.rst
setup.py
django_ses/__init__.py
django_ses/admin.py
django_ses/models.py
django_ses/settings.py
django_ses/signals.py
django_ses/urls.py
django_ses/utils.py
django_ses/views.py
django_ses/management/__init__.py
django_ses/management/commands/__init__.py
django_ses/management/commands/get_ses_statistics.py
django_ses/management/commands/ses_email_address.py
django_ses/templates/django_ses/send_stats.html
django_ses3.egg-info/PKG-INFO
django_ses3.egg-info/SOURCES.txt
django_ses3.egg-info/dependency_links.txt
django_ses3.egg-info/requires.txt
django_ses3.egg-info/top_level.txt
example/__init__.py
example/local_settings.template.py
example/manage.py
example/middleware.py
example/settings.py
example/urls.py
example/views.py
example/templates/base.html
example/templates/index.html
example/templates/send-email.html
tests/__init__.py
tests/settings.py
tests/test_backend.py
tests/test_commands.py
tests/test_settings.py
tests/test_stats.py
tests/test_verifier.py
tests/test_views.py
tests/urls.py
tests/utils.py