Metadata-Version: 1.1
Name: django-ses3
Version: 0.7.0
Summary: A Django email backend for Amazon's Simple Email Service
Home-page: http://github.com/tricoder42/django-ses/
Author: Tomáš Ehrlich
Author-email: tomas.ehrlich@gmail.com
License: MIT
Platform: any
Classifier: Development Status :: 4 - Beta
Classifier: Intended Audience :: Developers
Classifier: License :: OSI Approved :: MIT License
Classifier: Operating System :: OS Independent
Classifier: Programming Language :: Python
Classifier: Topic :: Software Development :: Libraries :: Python Modules
Classifier: Framework :: Django
